memegen/__init__.py
memegen/__main__.py
memegen/cli.py
memegen/gui.py
memegen/tests/__init__.py
memegen/tests/conftest.py
memegen/tests/test_utils.py
memegen/utils.py
memegen_client-0.0.dist-info/entry_points.txt
memegen_client-0.0.dist-info/LICENSE.md
memegen_client-0.0.dist-info/WHEEL
memegen_client-0.0.dist-info/METADATA
memegen_client-0.0.dist-info/RECORD
