Metadata-Version: 2.1
Name: memegen-client
Version: 0.0
Summary: The official Python client for Memegen.link
Home-page: https://pypi.org/project/memegen-client
License: MIT
Author: Jace Browning
Author-email: jacebrowning@gmail.com
Requires-Python: >=3.9,<4.0
Classifier: Development Status :: 1 - Planning
Classifier: License :: OSI Approved :: MIT License
Classifier: Natural Language :: English
Classifier: Operating System :: OS Independent
Classifier: Programming Language :: Python
Classifier: Programming Language :: Python :: 3
Classifier: Programming Language :: Python :: 3.10
Classifier: Programming Language :: Python :: 3.9
Requires-Dist: click (>=7.0,<8.0)
Requires-Dist: minilog (>=2.0,<3.0)
Project-URL: Documentation, https://memegen-client.readthedocs.io
Project-URL: Repository, https://github.com/jacebrowning/memegen-client
